typinox/__init__.py
typinox/_helper.py
typinox/_module.py
typinox/_vmapped.py
typinox/debug.py
typinox/error.py
typinox/module.py
typinox/shaped.py
typinox/tree.py
typinox/validator.py
typinox/vmapped.py
typinox-0.4.0.dist-info/METADATA
typinox-0.4.0.dist-info/WHEEL
typinox-0.4.0.dist-info/licenses/LICENSE
typinox-0.4.0.dist-info/RECORD
