Metadata-Version: 2.4
Name: typinox
Version: 0.4.0
Summary: Enhanced runtime type-checked JAX modules
Project-URL: repository, https://github.com/EtaoinWu/typinox
Author-email: Etaoin Wu <me@etaoinwu.com>
License: BSD 3-Clause License
License-File: LICENSE
Keywords: annotations,deep-learning,equinox,jax,neural-networks,type-checking,typing
Classifier: Development Status :: 3 - Alpha
Classifier: Intended Audience :: Developers
Classifier: Intended Audience :: Financial and Insurance Industry
Classifier: Intended Audience :: Information Technology
Classifier: Intended Audience :: Science/Research
Classifier: License :: OSI Approved :: BSD License
Classifier: Natural Language :: English
Classifier: Programming Language :: Python :: 3
Classifier: Programming Language :: Python :: 3.14
Classifier: Topic :: Scientific/Engineering :: Artificial Intelligence
Classifier: Topic :: Scientific/Engineering :: Mathematics
Requires-Python: >=3.14
Requires-Dist: beartype>=0.22.5
Requires-Dist: equinox<0.14.0,>=0.13.2
Requires-Dist: jax<0.9.0,>=0.8.0
Requires-Dist: jaxtyping<0.4.0,>=0.3.3
Provides-Extra: docs
Requires-Dist: sphinx-book-theme<2.0,>=1.1.4; extra == 'docs'
Requires-Dist: sphinx<9.0,>=8.2.3; extra == 'docs'
